{
  "fecha": "22/07/2026",
  "provisorio": false,
  "inmag": 4555.461,
  "igmag": 3810.124,
  "totalCabezas": 3399,
  "categorias": [
    {
      "cat": "NOVILLOS Mest.EyB 431/460",
      "min": 4250,
      "max": 4880,
      "prom": 4694.332,
      "cabezas": 103
    },
    {
      "cat": "NOVILLOS Mest.EyB 461/490",
      "min": 4720,
      "max": 4800,
      "prom": 4770.576,
      "cabezas": 126
    },
    {
      "cat": "NOVILLOS Mest.EyB 491/520",
      "min": 4600,
      "max": 4800,
      "prom": 4683.403,
      "cabezas": 33
    },
    {
      "cat": "NOVILLOS Mest.EyB + 520",
      "min": 4200,
      "max": 4900,
      "prom": 4512.054,
      "cabezas": 127
    },
    {
      "cat": "NOVILLOS Regulares Pes.",
      "min": 3900,
      "max": 4220,
      "prom": 4037.113,
      "cabezas": 68
    },
    {
      "cat": "NOVILLITOS EyB M. 300/390",
      "min": 3200,
      "max": 5300,
      "prom": 4749.628,
      "cabezas": 344
    },
    {
      "cat": "NOVILLITOS EyB P. 391/430",
      "min": 3000,
      "max": 5000,
      "prom": 4550.172,
      "cabezas": 234
    },
    {
      "cat": "NOVILLITOS Regulares",
      "min": 3500,
      "max": 4850,
      "prom": 4251.865,
      "cabezas": 61
    },
    {
      "cat": "VAQUILLONAS EyB M.270/390",
      "min": 3800,
      "max": 5400,
      "prom": 4892.997,
      "cabezas": 481
    },
    {
      "cat": "VAQUILLONAS EyB P.391/430",
      "min": 2400,
      "max": 4850,
      "prom": 4148.866,
      "cabezas": 133
    },
    {
      "cat": "VAQUILLONAS Regulares",
      "min": 3700,
      "max": 4600,
      "prom": 4112.492,
      "cabezas": 296
    },
    {
      "cat": "VACAS Buenas",
      "min": 2200,
      "max": 4000,
      "prom": 3246.784,
      "cabezas": 528
    },
    {
      "cat": "VACAS Regulares",
      "min": 1800,
      "max": 3700,
      "prom": 2675.631,
      "cabezas": 587
    },
    {
      "cat": "VACAS Conserva Buena",
      "min": 2100,
      "max": 2800,
      "prom": 2553.69,
      "cabezas": 99
    },
    {
      "cat": "VACAS Conserva Inferior",
      "min": 2400,
      "max": 2500,
      "prom": 2174.669,
      "cabezas": 25
    },
    {
      "cat": "TOROS Buenos",
      "min": 2900,
      "max": 3600,
      "prom": 2961.621,
      "cabezas": 57
    },
    {
      "cat": "TOROS Regulares",
      "min": 3200,
      "max": 3200,
      "prom": 2771.814,
      "cabezas": 28
    },
    {
      "cat": "MEJ EyB",
      "min": 4100,
      "max": 4900,
      "prom": 4115.564,
      "cabezas": 36
    },
    {
      "cat": "MEJ Regulares",
      "min": 2350,
      "max": 4300,
      "prom": 2753.018,
      "cabezas": 33
    }
  ],
  "fuente": "Mercado Agroganadero (MAG) — Cañuelas"
}