{
  "fecha": "2026-07-06",
  "flash": [
    {
      "grano": "Trigo",
      "categorias": [
        {
          "titulo": "Disponibles",
          "filas": [
            {
              "mercado": "Rosario $/t",
              "posicion": "07/07",
              "varDir": "down",
              "precio": "291.100"
            },
            {
              "mercado": "A3 Mercados",
              "posicion": "06/07",
              "varDir": "up",
              "precio": "301.000"
            }
          ]
        },
        {
          "titulo": "Futuros A3 Mercados",
          "filas": [
            {
              "mercado": "Rosario Jul US$/t",
              "posicion": "07/07",
              "varDir": "up",
              "precio": "204"
            }
          ]
        },
        {
          "titulo": "FOB MAGyP",
          "filas": [
            {
              "mercado": "Spot US$/t",
              "posicion": "07/07",
              "varDir": "down",
              "precio": "227"
            }
          ]
        },
        {
          "titulo": "CBOT",
          "filas": [
            {
              "mercado": "Jul. US$/t",
              "posicion": "07/07",
              "varDir": "down",
              "precio": "223,87"
            }
          ]
        },
        {
          "titulo": "FAS MAGyP",
          "filas": [
            {
              "mercado": "Valor de Mercado",
              "posicion": "07/07",
              "varDir": "down",
              "precio": "289.452"
            }
          ]
        }
      ]
    },
    {
      "grano": "Maíz",
      "categorias": [
        {
          "titulo": "Disponibles",
          "filas": [
            {
              "mercado": "Rosario $/t",
              "posicion": "07/07",
              "varDir": "up",
              "precio": "268.900"
            },
            {
              "mercado": "A3 Mercados",
              "posicion": "06/07",
              "varDir": "up",
              "precio": "270.000"
            }
          ]
        },
        {
          "titulo": "Futuros A3 Mercados",
          "filas": [
            {
              "mercado": "Rosario Ago US$/t",
              "posicion": "07/07",
              "varDir": "up",
              "precio": "183"
            }
          ]
        },
        {
          "titulo": "FOB MAGyP",
          "filas": [
            {
              "mercado": "Spot US$/t",
              "posicion": "07/07",
              "varDir": "up",
              "precio": "207"
            }
          ]
        },
        {
          "titulo": "CBOT",
          "filas": [
            {
              "mercado": "Jul. US$/t",
              "posicion": "07/07",
              "varDir": "up",
              "precio": "174,21"
            }
          ]
        },
        {
          "titulo": "FAS MAGyP",
          "filas": [
            {
              "mercado": "Valor de Mercado",
              "posicion": "07/07",
              "varDir": "up",
              "precio": "260.578"
            }
          ]
        }
      ]
    },
    {
      "grano": "Soja",
      "categorias": [
        {
          "titulo": "Disponibles",
          "filas": [
            {
              "mercado": "Rosario $/t",
              "posicion": "07/07",
              "varDir": "up",
              "precio": "480.500"
            },
            {
              "mercado": "A3 Mercados",
              "posicion": "06/07",
              "varDir": "up",
              "precio": "482.000"
            }
          ]
        },
        {
          "titulo": "Futuros A3 Mercados",
          "filas": [
            {
              "mercado": "Rosario Jul US$/t",
              "posicion": "07/07",
              "varDir": "up",
              "precio": "327,7"
            }
          ]
        },
        {
          "titulo": "FOB MAGyP",
          "filas": [
            {
              "mercado": "Spot US$/t",
              "posicion": "07/07",
              "varDir": "up",
              "precio": "447"
            }
          ]
        },
        {
          "titulo": "CBOT",
          "filas": [
            {
              "mercado": "Jul. US$/t",
              "posicion": "07/07",
              "varDir": "up",
              "precio": "439,74"
            }
          ]
        },
        {
          "titulo": "FAS MAGyP",
          "filas": [
            {
              "mercado": "Valor de Mercado",
              "posicion": "07/07",
              "varDir": "up",
              "precio": "495.633"
            }
          ]
        }
      ]
    },
    {
      "grano": "Girasol",
      "categorias": [
        {
          "titulo": "Disponibles",
          "filas": [
            {
              "mercado": "Rosario $/t",
              "posicion": "07/07",
              "varDir": "igual",
              "precio": "665.550"
            },
            {
              "mercado": "Disponible US$/t",
              "posicion": "06/07",
              "varDir": "igual",
              "precio": "655.000"
            }
          ]
        },
        {
          "titulo": "Futuros A3 Mercados",
          "filas": [
            {
              "mercado": "Disponible",
              "posicion": "",
              "varDir": "igual",
              "precio": "s/c"
            }
          ]
        },
        {
          "titulo": "FOB MAGyP",
          "filas": [
            {
              "mercado": "Spot US$/t",
              "posicion": "29/06",
              "varDir": "up",
              "precio": "492"
            }
          ]
        },
        {
          "titulo": "FAS MAGyP",
          "filas": [
            {
              "mercado": "Valor de Mercado",
              "posicion": "07/07",
              "varDir": "up",
              "precio": "592.889"
            }
          ]
        }
      ]
    }
  ],
  "dolar": {
    "compra": 1483,
    "venta": 1492
  }
}